{
  "version": "5.5.0",
  "flags": {
    "plate_type": "CHN",
    "plate_number": "皖AM1015",
    "angle": {
      "x": -32.34,
      "y": -58.04,
      "z": 21.45
    },
    "normvec_camaxis_angle": 63.43
  },
  "shapes": [
    {
      "label": "plate",
      "points": [
        [
          310.0537109375,
          476.1044616699219
        ],
        [
          376.6745910644531,
          501.877197265625
        ],
        [
          382.238037109375,
          544.1334838867188
        ],
        [
          314.30694580078125,
          517.0702514648438
        ]
      ],
      "group_id": null,
      "description": "",
      "shape_type": "polygon",
      "flags": {},
      "mask": null
    }
  ],
  "imagePath": "0068-20_27-307&474_385&547-385&547_312&519_307&474_380&502-0_0_11_25_24_25_29-114-22.jpg",
  "imageData": null,
  "imageHeight": 1160,
  "imageWidth": 720
}